pagpdf/__init__.py
pagpdf/__main__.py
pagpdf-0.9.2.dist-info/entry_points.txt
pagpdf-0.9.2.dist-info/WHEEL
pagpdf-0.9.2.dist-info/METADATA
pagpdf-0.9.2.dist-info/RECORD
